hetdex_api/__init__.py
hetdex_api/amp_widget.py
hetdex_api/config.py
hetdex_api/cube_widget.py
hetdex_api/detections.py
hetdex_api/detwidgets.py
hetdex_api/elixer.py
hetdex_api/elixer_widget_cls.py
hetdex_api/elixer_widget_for.py
hetdex_api/elixer_widget_lae.py
hetdex_api/elixer_widget_spur.py
hetdex_api/elixer_widgets.py
hetdex_api/extinction.py
hetdex_api/extract.py
hetdex_api/file_handling.py
hetdex_api/input_utils.py
hetdex_api/mask.py
hetdex_api/qc.py
hetdex_api/query_widget.py
hetdex_api/shot.py
hetdex_api/sqlite_utils.py
hetdex_api/survey.py
hetdex_api/flux_limits/__init__.py
hetdex_api/flux_limits/collapse_cubes.py
hetdex_api/flux_limits/flim_model_cache.py
hetdex_api/flux_limits/flim_models.py
hetdex_api/flux_limits/flim_models_old.py
hetdex_api/flux_limits/generate_simulation_inputs.py
hetdex_api/flux_limits/hdf5_sensitivity_cubes.py
hetdex_api/flux_limits/sensitivity_cube.py
hetdex_api/flux_limits/shot_sensitivity.py
hetdex_api/mask_tools/__init__.py
hetdex_api/mask_tools/amplifier_positions.py
hetdex_api/mask_tools/generate_sky_masks.py
hetdex_tools/__init__.py
hetdex_tools/amp_flag.py
hetdex_tools/cal_on_karl_results.py
hetdex_tools/compute_average_one_sigma.py
hetdex_tools/extracth5.py
hetdex_tools/fit_polynomial_to_sn_scaling.py
hetdex_tools/fof_kdtree.py
hetdex_tools/galmask.py
hetdex_tools/get_contour.py
hetdex_tools/get_rsp_spec.py
hetdex_tools/get_shots_of_interest.py
hetdex_tools/get_spec.py
hetdex_tools/get_spec2D.py
hetdex_tools/hdf5_visualize_ds9.py
hetdex_tools/hetillum.py
hetdex_tools/interpolate.py
hetdex_tools/line_fitting.py
hetdex_tools/make_curated_catalog.py
hetdex_tools/make_flim_mask.py
hetdex_tools/make_regions.py
hetdex_tools/mcmc_gauss.py
hetdex_tools/phot_tools.py
hetdex_tools/plot_compl_file.py
hetdex_tools/plot_flim_slice.py
hetdex_tools/plot_flux_limit_v_detections.py
hetdex_tools/source_catalog.py
hetdex_api-0.8.7.dist-info/METADATA
hetdex_api-0.8.7.dist-info/WHEEL
hetdex_api-0.8.7.dist-info/entry_points.txt
hetdex_api-0.8.7.dist-info/top_level.txt
hetdex_api-0.8.7.dist-info/RECORD
