Metadata-Version: 2.1
Name: hetdex-api
Version: 0.8.7
Summary: Tools to deal with HETDEX data releases
Home-page: https://github.com/HETDEX/hetdex_api
Author: The HETDEX Collaboration
Author-email: erin@astro.as.utexas.edu
License: UNKNOWN
Download-URL: https://github.com/HETDEX/hetdex_api/archive/0.8.2.tar.gz
Platform: UNKNOWN
Classifier: Development Status :: 3 - Alpha
Classifier: Environment :: Console
Classifier: Intended Audience :: Developers
Classifier: Intended Audience :: Science/Research
Classifier: License :: OSI Approved :: GNU General Public License (GPL)
Classifier: Operating System :: Unix
Classifier: Programming Language :: Python :: 3.7
Classifier: Topic :: Scientific/Engineering :: Astronomy
Classifier: Topic :: Utilities
Requires-Dist: numpy
Requires-Dist: astropy (!=1.3.3,>=1.2)
Requires-Dist: astroquery
Requires-Dist: scipy (>=0.17.0)
Requires-Dist: regions
Requires-Dist: tables
Requires-Dist: ipywidgets
Requires-Dist: astrowidgets
Requires-Dist: healpy
Requires-Dist: nway
Requires-Dist: dustmaps
Requires-Dist: extinction
Provides-Extra: doc
Requires-Dist: sphinx ; extra == 'doc'
Requires-Dist: sphinx-markdown-tables ; extra == 'doc'
Requires-Dist: sphinx-argparse ; extra == 'doc'
Requires-Dist: sphinx-rtd-theme ; extra == 'doc'
